[
  { "name": "Python", "icon": "python", "bgColor": "#3776AB" },
  { "name": "FastAPI", "icon": "api", "bgColor": "#009688" },
  {
    "name": "Django",
    "iconUrl": "https://cdn.jsdelivr.net/gh/devicons/devicon/icons/django/django-plain.svg",
    "bgColor": "#092E20",
    "iconBg": "dark"
  },
  { "name": "JavaScript", "icon": "javascript", "bgColor": "#F7DF1E" },
  { "name": "TypeScript", "icon": "typescript", "bgColor": "#3178C6" },
  { "name": "React", "icon": "react", "bgColor": "#20232A" },
  {
    "name": "Next.js",
    "iconUrl": "https://cdn.jsdelivr.net/gh/devicons/devicon/icons/nextjs/nextjs-original.svg",
    "bgColor": "#000000",
    "iconBg": "dark"
  },
  {
    "name": "PostgreSQL",
    "iconUrl": "https://cdn.jsdelivr.net/gh/devicons/devicon/icons/postgresql/postgresql-original.svg",
    "bgColor": "#336791"
  },
  {
    "name": "Redis",
    "iconUrl": "https://cdn.jsdelivr.net/gh/devicons/devicon/icons/redis/redis-original.svg",
    "bgColor": "#DC382D"
  },
  {
    "name": "Docker",
    "iconUrl": "https://cdn.jsdelivr.net/gh/devicons/devicon/icons/docker/docker-original.svg",
    "bgColor": "#2496ED"
  },
  {
    "name": "AWS",
    "iconUrl": "https://cdn.jsdelivr.net/gh/devicons/devicon/icons/amazonwebservices/amazonwebservices-plain-wordmark.svg",
    "bgColor": "#232F3E"
  },
  { "name": "GraphQL", "icon": "graphql", "bgColor": "#E10098", "iconBg": "light" },
  {
    "name": "Supabase",
    "iconUrl": "https://cdn.jsdelivr.net/gh/devicons/devicon/icons/supabase/supabase-original.svg",
    "bgColor": "#3ECF8E",
    "iconBg": "light"
  },
  { "name": "Git", "icon": "git", "bgColor": "#F05032" }
]
